pgrepup/__init__.py
pgrepup/cli.py
pgrepup/config.py
pgrepup/version.py
pgrepup/commands/__init__.py
pgrepup/commands/check.py
pgrepup/commands/config.py
pgrepup/commands/fix.py
pgrepup/commands/setup.py
pgrepup/commands/start.py
pgrepup/commands/status.py
pgrepup/commands/stop.py
pgrepup/commands/uninstall.py
pgrepup/helpers/__init__.py
pgrepup/helpers/crypt.py
pgrepup/helpers/database.py
pgrepup/helpers/docopt_dispatch.py
pgrepup/helpers/operation_target.py
pgrepup/helpers/replication.py
pgrepup/helpers/ui.py
pgrepup/helpers/utils.py
pgrepup-0.3.10.data/scripts/pgrepup
pgrepup-0.3.10.dist-info/DESCRIPTION.rst
pgrepup-0.3.10.dist-info/METADATA
pgrepup-0.3.10.dist-info/RECORD
pgrepup-0.3.10.dist-info/WHEEL
pgrepup-0.3.10.dist-info/metadata.json
pgrepup-0.3.10.dist-info/top_level.txt
