Metadata-Version: 2.0
Name: pgrepup
Version: 0.3.10
Summary: Upgrade PostgreSQL clusters using logical replication
Home-page: https://www.github.com/rtshome/pgrepup
Author: Denis Gasparin
Author-email: denis@gasparin.net
License: GPL-3.0
Platform: Linux
Platform: Mac OS X
Classifier: Environment :: Console
Classifier: Development Status :: 5 - Production/Stable
Classifier: Topic :: Database
Classifier: Topic :: System :: Recovery Tools
Classifier: Intended Audience :: System Administrators
Classifier: License :: OSI Approved :: GNU General Public License v3 or later (GPLv3+)
Classifier: Programming Language :: Python
Classifier: Programming Language :: Python :: 2.6
Classifier: Programming Language :: Python :: 2.7
Classifier: Programming Language :: Python :: 3.3
Classifier: Programming Language :: Python :: 3.4
Classifier: Programming Language :: Python :: 3.5
Requires-Dist: clint (>=0.5.1)
Requires-Dist: cryptography
Requires-Dist: docopt (>=0.6.0)
Requires-Dist: psycopg2-binary (>=2.4.2)
Requires-Dist: python-dateutil
Requires-Dist: semver
